proxystore/__init__.py
proxystore/ex.py
proxystore/factory.py
proxystore/mypy_plugin.py
proxystore/py.typed
proxystore/serialize.py
proxystore/warnings.py
proxystore/connectors/__init__.py
proxystore/connectors/dim.py
proxystore/connectors/endpoint.py
proxystore/connectors/file.py
proxystore/connectors/globus.py
proxystore/connectors/local.py
proxystore/connectors/multi.py
proxystore/connectors/protocols.py
proxystore/connectors/redis.py
proxystore/endpoint/__init__.py
proxystore/endpoint/cli.py
proxystore/endpoint/client.py
proxystore/endpoint/commands.py
proxystore/endpoint/config.py
proxystore/endpoint/constants.py
proxystore/endpoint/endpoint.py
proxystore/endpoint/exceptions.py
proxystore/endpoint/messages.py
proxystore/endpoint/serve.py
proxystore/endpoint/storage.py
proxystore/globus/__init__.py
proxystore/globus/app.py
proxystore/globus/cli.py
proxystore/globus/client.py
proxystore/globus/scopes.py
proxystore/p2p/__init__.py
proxystore/p2p/chunks.py
proxystore/p2p/connection.py
proxystore/p2p/exceptions.py
proxystore/p2p/manager.py
proxystore/p2p/nat.py
proxystore/p2p/relay/__init__.py
proxystore/p2p/relay/authenticate.py
proxystore/p2p/relay/client.py
proxystore/p2p/relay/config.py
proxystore/p2p/relay/exceptions.py
proxystore/p2p/relay/manager.py
proxystore/p2p/relay/messages.py
proxystore/p2p/relay/run.py
proxystore/p2p/relay/server.py
proxystore/proxy/__init__.py
proxystore/proxy/_property.py
proxystore/proxy/_utils.py
proxystore/store/__init__.py
proxystore/store/base.py
proxystore/store/cache.py
proxystore/store/config.py
proxystore/store/exceptions.py
proxystore/store/executor.py
proxystore/store/factory.py
proxystore/store/future.py
proxystore/store/lifetimes.py
proxystore/store/metrics.py
proxystore/store/ref.py
proxystore/store/scopes.py
proxystore/store/types.py
proxystore/store/utils.py
proxystore/stream/__init__.py
proxystore/stream/_consumer.py
proxystore/stream/_producer.py
proxystore/stream/events.py
proxystore/stream/exceptions.py
proxystore-0.8.3.dist-info/licenses/LICENSE
proxystore-0.8.3.dist-info/METADATA
proxystore-0.8.3.dist-info/WHEEL
proxystore-0.8.3.dist-info/entry_points.txt
proxystore-0.8.3.dist-info/top_level.txt
proxystore-0.8.3.dist-info/RECORD
