Metadata-Version: 2.4
Name: proxystore
Version: 0.8.3
Summary: Advanced data flow management for distributed Python applications
Author: Globus Labs
Author-email: Greg Pauloski <jgpauloski@uchicago.edu>
Maintainer-email: Greg Pauloski <jgpauloski@uchicago.edu>, Valerie Hayot-Sasson <vhayot@uchicago.edu>
License: MIT
Project-URL: Homepage, https://proxystore.dev
Project-URL: Documentation, https://docs.proxystore.dev
Project-URL: Source, https://github.com/proxystore/proxystore
Classifier: License :: OSI Approved :: MIT License
Classifier: Programming Language :: Python :: 3.9
Classifier: Programming Language :: Python :: 3.10
Classifier: Programming Language :: Python :: 3.11
Classifier: Programming Language :: Python :: 3.12
Classifier: Programming Language :: Python :: 3.13
Classifier: Programming Language :: Python :: 3 :: Only
Classifier: Programming Language :: Python :: Implementation :: CPython
Requires-Python: >=3.9
License-File: LICENSE
Requires-Dist: click!=8.1.4
Requires-Dist: cloudpickle>=3
Requires-Dist: cryptography>=39.0.1
Requires-Dist: globus-sdk<4,>=3.46.0
Requires-Dist: pydantic<3,>=2
Requires-Dist: tomli; python_version < "3.11"
Requires-Dist: tomli-w
Requires-Dist: typing-extensions>=4.3.0; python_version < "3.11"
Provides-Extra: all
Requires-Dist: proxystore[endpoints,extensions,kafka,redis,zmq]; extra == "all"
Provides-Extra: endpoints
Requires-Dist: aiortc>=1.3.2; extra == "endpoints"
Requires-Dist: aiosqlite; extra == "endpoints"
Requires-Dist: uvicorn[standard]; extra == "endpoints"
Requires-Dist: psutil; extra == "endpoints"
Requires-Dist: pystun3; extra == "endpoints"
Requires-Dist: python-daemon; extra == "endpoints"
Requires-Dist: quart>=0.18.0; extra == "endpoints"
Requires-Dist: requests>=2.27.1; extra == "endpoints"
Requires-Dist: websockets>=14; extra == "endpoints"
Provides-Extra: extensions
Requires-Dist: proxystore-ex; extra == "extensions"
Provides-Extra: kafka
Requires-Dist: confluent-kafka; extra == "kafka"
Provides-Extra: redis
Requires-Dist: redis>=3.4; extra == "redis"
Provides-Extra: zmq
Requires-Dist: pyzmq; extra == "zmq"
Provides-Extra: dev
Requires-Dist: covdefaults>=2.2; extra == "dev"
Requires-Dist: coverage!=7.6.2; extra == "dev"
Requires-Dist: mypy; extra == "dev"
Requires-Dist: numpy; extra == "dev"
Requires-Dist: pandas; extra == "dev"
Requires-Dist: polars; extra == "dev"
Requires-Dist: pre-commit; extra == "dev"
Requires-Dist: pytest; extra == "dev"
Requires-Dist: pytest-asyncio>=0.23.2; extra == "dev"
Requires-Dist: pytest-cov; extra == "dev"
Requires-Dist: pytest-timeout; extra == "dev"
Requires-Dist: ruff>=0.2.0; extra == "dev"
Requires-Dist: tox; extra == "dev"
Requires-Dist: types-psutil; extra == "dev"
Requires-Dist: types-redis; extra == "dev"
Requires-Dist: types-requests; extra == "dev"
Requires-Dist: virtualenv; extra == "dev"
Provides-Extra: docs
Requires-Dist: black==25.1.0; extra == "docs"
Requires-Dist: griffe==1.7.3; extra == "docs"
Requires-Dist: mkdocs-click==0.9.0; extra == "docs"
Requires-Dist: mkdocs-gen-files==0.5.0; extra == "docs"
Requires-Dist: mkdocs-literate-nav==0.6.2; extra == "docs"
Requires-Dist: mkdocs-material==9.6.12; extra == "docs"
Requires-Dist: mkdocs-section-index==0.3.10; extra == "docs"
Requires-Dist: mkdocstrings==0.29.1; extra == "docs"
Requires-Dist: mkdocstrings-python==1.16.12; extra == "docs"
Requires-Dist: mike==2.1.3; extra == "docs"
Requires-Dist: proxystore[endpoints]; extra == "docs"
Dynamic: license-file
